vidify/__init__.py
vidify/__main__.py
vidify/audiosync.py
vidify/config.py
vidify/lyrics.py
vidify/version.py
vidify/youtube.py
vidify/api/__init__.py
vidify/api/generic.py
vidify/api/mpris.py
vidify/api/spotify/__init__.py
vidify/api/spotify/swspotify.py
vidify/api/spotify/web.py
vidify/gui/__init__.py
vidify/gui/components.py
vidify/gui/window.py
vidify/gui/api/__init__.py
vidify/gui/api/spotify_web.py
vidify/gui/res/cross.svg
vidify/gui/res/dark_mode_cross.svg
vidify/gui/res/default_video.mp4
vidify/gui/res/icon.svg
vidify/gui/res/icon16x16.ico
vidify/gui/res/Inter/Inter-Bold.otf
vidify/gui/res/Inter/Inter-Bold.ttf
vidify/gui/res/Inter/Inter-BoldItalic.otf
vidify/gui/res/Inter/Inter-BoldItalic.ttf
vidify/gui/res/Inter/Inter-Italic.otf
vidify/gui/res/Inter/Inter-Italic.ttf
vidify/gui/res/Inter/Inter-Medium.otf
vidify/gui/res/Inter/Inter-Medium.ttf
vidify/gui/res/Inter/Inter-MediumItalic.otf
vidify/gui/res/Inter/Inter-MediumItalic.ttf
vidify/gui/res/Inter/Inter-Regular.otf
vidify/gui/res/Inter/Inter-Regular.ttf
vidify/gui/res/Inter/LICENSE.txt
vidify/gui/res/api_icons/mpris.svg
vidify/gui/res/api_icons/spotify/swspotify.svg
vidify/gui/res/api_icons/spotify/web.svg
vidify/gui/res/player_icons/external.svg
vidify/gui/res/player_icons/mpv.svg
vidify/gui/res/player_icons/vlc.svg
vidify/player/__init__.py
vidify/player/external.py
vidify/player/generic.py
vidify/player/mpv.py
vidify/player/vlc.py
vidify-2.2.6.data/data/share/applications/vidify.desktop
vidify-2.2.6.data/data/share/pixmaps/vidify.svg
vidify-2.2.6.dist-info/LICENSE.LGPL
vidify-2.2.6.dist-info/METADATA
vidify-2.2.6.dist-info/WHEEL
vidify-2.2.6.dist-info/entry_points.txt
vidify-2.2.6.dist-info/top_level.txt
vidify-2.2.6.dist-info/RECORD
