Metadata-Version: 2.1
Name: vidify
Version: 2.2.6
Summary: Watch music videos in real-time for the songs playing on your device
Home-page: https://vidify.org/
Author: Mario O.M.
Author-email: marioortizmanero@gmail.com
Maintainer: Mario O.M.
Maintainer-email: marioortizmanero@gmail.com
License: LGPL
Keywords: spotify music video player videos lyrics linux windows macos
Platform: UNKNOWN
Classifier: Development Status :: 5 - Production/Stable
Classifier: Intended Audience :: End Users/Desktop
Classifier: Topic :: Multimedia :: Sound/Audio :: Players
Classifier: License :: OSI Approved :: GNU Lesser General Public License v3 (LGPLv3)
Classifier: Programming Language :: Python :: 3
Classifier: Programming Language :: Python :: 3.7
Classifier: Programming Language :: Python :: 3.8
Requires-Python: >=3.6
Requires-Dist: QtPy
Requires-Dist: lyricwikia
Requires-Dist: youtube-dl
Requires-Dist: appdirs
Requires-Dist: qdarkstyle
Requires-Dist: python-vlc
Requires-Dist: tekore (==3.*)
Requires-Dist: zeroconf
Requires-Dist: PyQt5
Requires-Dist: PyQtWebEngine (>=5.14.0)
Requires-Dist: pydbus ; platform_system == "Linux"
Requires-Dist: SwSpotify (>=1.1.1) ; platform_system == "Windows" or platform_system == "Darwin"
Requires-Dist: dataclasses ; python_version < "3.7"
Provides-Extra: audiosync
Requires-Dist: vidify-audiosync (==0.3.*) ; extra == 'audiosync'
Provides-Extra: dev
Requires-Dist: flake8 ; extra == 'dev'
Requires-Dist: pyinstaller ; extra == 'dev'
Provides-Extra: mpv
Requires-Dist: python-mpv ; extra == 'mpv'
